ig/__init__.py
ig/cli.py
igprasad-0.1.7.dist-info/METADATA
igprasad-0.1.7.dist-info/WHEEL
igprasad-0.1.7.dist-info/entry_points.txt
igprasad-0.1.7.dist-info/top_level.txt
igprasad-0.1.7.dist-info/RECORD
