Metadata-Version: 2.4
Name: igprasad
Version: 0.1.7
Summary: A command-line tool to run predefined Python and R programs.
Home-page: https://github.com/igprasad09/pip-igprasad
Author: godl
License: MIT
Keywords: cli python r learning
Classifier: Programming Language :: Python :: 3
Classifier: License :: OSI Approved :: MIT License
Classifier: Operating System :: OS Independent
Requires-Python: >=3.10
Dynamic: author
Dynamic: classifier
Dynamic: description
Dynamic: description-content-type
Dynamic: home-page
Dynamic: keywords
Dynamic: license
Dynamic: requires-python
Dynamic: summary
